semantic_forms/docs/__init__.py
semantic_forms/docs/admin.py
semantic_forms/docs/apps.py
semantic_forms/docs/forms.py
semantic_forms/docs/models.py
semantic_forms/docs/views.py
semantic_forms/__init__.py
semantic_forms/fields.py
semantic_forms/filters/__init__.py
semantic_forms/filters/filters.py
semantic_forms/filters/filterset.py
semantic_forms/forms.py
semantic_forms/static/semantic_forms/semanticCalendar.js
semantic_forms/static/semantic_forms/semanticCheckbox.js
semantic_forms/static/semantic_forms/semanticChooser.js
semantic_forms/static/semantic_forms/semanticDropdown.js
semantic_forms/static/semantic_forms/semanticTranslatedCalendar.js
semantic_forms/static/semantic_forms/semanticUntranslatedCalendar.js
semantic_forms/static/semantic_forms/unsemantic.css
semantic_forms/templates/semantic_forms/base.html
semantic_forms/templates/semantic_forms/demo/kitchen_sink.html
semantic_forms/templates/semantic_forms/forms/semantic_form.html
semantic_forms/templates/semantic_forms/forms/widgets/checkbox.html
semantic_forms/templates/semantic_forms/forms/widgets/checkbox_option.html
semantic_forms/templates/semantic_forms/forms/widgets/checkbox_select.html
semantic_forms/templates/semantic_forms/forms/widgets/chooser.html
semantic_forms/templates/semantic_forms/forms/widgets/clearable_file_input.html
semantic_forms/templates/semantic_forms/forms/widgets/date.html
semantic_forms/templates/semantic_forms/forms/widgets/datetime.html
semantic_forms/templates/semantic_forms/forms/widgets/input_autocomplete_off.html
semantic_forms/templates/semantic_forms/forms/widgets/input_option.html
semantic_forms/templates/semantic_forms/forms/widgets/multiwidget.html
semantic_forms/templates/semantic_forms/forms/widgets/radio.html
semantic_forms/templates/semantic_forms/forms/widgets/radio_option.html
semantic_forms/templates/semantic_forms/forms/widgets/select.html
semantic_forms/templates/semantic_forms/forms/widgets/select_time.html
django_semantic_forms-0.1.7.dist-info/LICENSE
django_semantic_forms-0.1.7.dist-info/METADATA
django_semantic_forms-0.1.7.dist-info/WHEEL
django_semantic_forms-0.1.7.dist-info/RECORD
